{"zingmp3.vn":{"/":{"zmp3_app_version.1":{"key":"zmp3_app_version.1","value":"1722","expires":"2023-08-23T09:07:28.000Z","maxAge":31536000,"domain":"zingmp3.vn","path":"/","hostOnly":false,"creation":"2022-08-23T09:07:28.415Z","lastAccessed":"2022-08-23T14:24:31.740Z"},"zmp3_rqid":{"key":"zmp3_rqid","value":"MHwxLjU0LjEzNC4yNDZ8MTmUsICyMnwxNjYxMjY0NjmUsICxMDU2","expires":"2022-10-27T14:24:31.000Z","maxAge":5616000,"domain":"zingmp3.vn","path":"/","hostOnly":false,"creation":"2022-08-23T09:07:28.431Z","lastAccessed":"2022-08-23T14:24:31.967Z"}}}}